tengri/__init__.py
tengri/weather.py
tengri/web.py
tengri-1.1.dist-info/LICENSE
tengri-1.1.dist-info/METADATA
tengri-1.1.dist-info/WHEEL
tengri-1.1.dist-info/entry_points.txt
tengri-1.1.dist-info/top_level.txt
tengri-1.1.dist-info/RECORD
